CHANGELOG
COPYRIGHT
LICENSE
MANIFEST.in
README.rst
setup.py
./__init__.py
./ir.py
./ir.xml
./res.py
./res.xml
./tryton.cfg
./icons/tryton-totp-key.svg
./tests/__init__.py
./tests/test_authentication_totp_optional.py
./view/user_form.xml
./view/user_form_preferences.xml
./view/user_setup_totp_done_form.xml
./view/user_setup_totp_skipped_form.xml
./view/user_setup_totp_start_form.xml
doc/conf.py
doc/design.rst
doc/index.rst
doc/installation.rst
doc/license.rst
doc/setup.rst
doc/support.rst
doc/usage.rst
trytonlq_authentication_totp_optional.egg-info/PKG-INFO
trytonlq_authentication_totp_optional.egg-info/SOURCES.txt
trytonlq_authentication_totp_optional.egg-info/dependency_links.txt
trytonlq_authentication_totp_optional.egg-info/entry_points.txt
trytonlq_authentication_totp_optional.egg-info/not-zip-safe
trytonlq_authentication_totp_optional.egg-info/requires.txt
trytonlq_authentication_totp_optional.egg-info/top_level.txt